abdwp/__init__.py
abdwp/book.py
abdwp/plot.py
abdwp/retrosheet.py
abdwp/statcast.py
abdwp/utils.py
abdwp/style/abdwp.mplstyle
abdwp-0.5.7.dist-info/METADATA
abdwp-0.5.7.dist-info/WHEEL
abdwp-0.5.7.dist-info/licenses/LICENSE
abdwp-0.5.7.dist-info/RECORD
