Metadata-Version: 2.4
Name: abdwp
Version: 0.5.7
Summary: Analyzing Baseball Data with Python
Author-email: David Dalpiaz <dalpiaz2@illinois.edu>
License-File: LICENSE
Requires-Python: >=3.12
Requires-Dist: numpy>=2.3.1
Requires-Dist: pandas>=2.3.0
Requires-Dist: requests>=2.32.4
